{
  "data": [
    {
      "War ID": 30940,
      "Status": "Active",
      "Start Date": "2025-09-19",
      "Start Time": "13:00",
      "End Date": "",
      "End Time": "",
      "Duration": "0m",
      "Target Score": 6000,
      "Faction 1 ID": 37426,
      "Faction 1 Name": "Monarch Embassy",
      "Faction 1 Score": 0,
      "Faction 1 Chain": 0,
      "Faction 1 Wars Won": 56,
      "Faction 1 Wars Lost": 43,
      "Faction 1 Win Rate": "57%",
      "Faction 1 Rank Value": 17,
      "Faction 1 Respect Value": 2083244,
      "Faction 1 HOF Chain Value": 1051,
      "Faction 1 Members": 22,
      "Faction 2 ID": 51926,
      "Faction 2 Name": "Inglorious Basterds",
      "Faction 2 Score": 0,
      "Faction 2 Chain": 0,
      "Faction 2 Wars Won": 60,
      "Faction 2 Wars Lost": 0,
      "Faction 2 Win Rate": "100%",
      "Faction 2 Rank Value": 17,
      "Faction 2 Respect Value": 1101266,
      "Faction 2 HOF Chain Value": 1000,
      "Faction 2 Members": 25,
      "Total Score": 0,
      "Winner Faction ID": "",
      "Last Updated Date": "2025-09-16",
      "Last Updated Time": "10:08",
      "Faction 1 Odds": 2.29,
      "Faction 1 Implied %": "43.63%",
      "Faction 1 True %": "43.63%",
      "Faction 1 Confidence": "95%",
      "Faction 1 Bet Example": "1 Xanax ($744,983) → $1,706,011 (+$961,028)",
      "Faction 2 Odds": 1.77,
      "Faction 2 Implied %": "56.37%",
      "Faction 2 True %": "56.37%",
      "Faction 2 Confidence": "95%",
      "Faction 2 Bet Example": "1 Xanax ($744,983) → $1,318,620 (+$573,637)",
      "Overall Confidence": "95%",
      "House Edge %": 6,
      "Rating Ratio": 0.8,
      "Odds Calculated At": "9/17/2025, 1:24:22 PM"
    },
    {
      "War ID": 30923,
      "Status": "Active",
      "Start Date": "2025-09-20",
      "Start Time": "15:00",
      "End Date": "",
      "End Time": "",
      "Duration": "0m",
      "Target Score": 14800,
      "Faction 1 ID": 31764,
      "Faction 1 Name": "39th Street Warriors",
      "Faction 1 Score": 0,
      "Faction 1 Chain": 0,
      "Faction 1 Wars Won": 35,
      "Faction 1 Wars Lost": 31,
      "Faction 1 Win Rate": "53%",
      "Faction 1 Rank Value": 17,
      "Faction 1 Respect Value": 5537814,
      "Faction 1 HOF Chain Value": 50000,
      "Faction 1 Members": 95,
      "Faction 2 ID": 46708,
      "Faction 2 Name": "The Revenant",
      "Faction 2 Score": 0,
      "Faction 2 Chain": 3,
      "Faction 2 Wars Won": 23,
      "Faction 2 Wars Lost": 16,
      "Faction 2 Win Rate": "59%",
      "Faction 2 Rank Value": 16,
      "Faction 2 Respect Value": 2540757,
      "Faction 2 HOF Chain Value": 25000,
      "Faction 2 Members": 98,
      "Total Score": 0,
      "Winner Faction ID": "",
      "Last Updated Date": "2025-09-16",
      "Last Updated Time": "10:08",
      "Faction 1 Odds": 1.58,
      "Faction 1 Implied %": "63.26%",
      "Faction 1 True %": "63.26%",
      "Faction 1 Confidence": "95%",
      "Faction 1 Bet Example": "1 Xanax ($744,983) → $1,177,073 (+$432,090)",
      "Faction 2 Odds": 2.72,
      "Faction 2 Implied %": "36.74%",
      "Faction 2 True %": "36.74%",
      "Faction 2 Confidence": "95%",
      "Faction 2 Bet Example": "1 Xanax ($744,983) → $2,026,354 (+$1,281,371)",
      "Overall Confidence": "95%",
      "House Edge %": 6,
      "Rating Ratio": 1.68,
      "Odds Calculated At": "9/17/2025, 1:24:24 PM"
    },
    {
      "War ID": 31063,
      "Status": "Active",
      "Start Date": "2025-09-20",
      "Start Time": "12:00",
      "End Date": "",
      "End Time": "",
      "Duration": "0m",
      "Target Score": 4400,
      "Faction 1 ID": 48757,
      "Faction 1 Name": "SYN - Brigata di Guerra",
      "Faction 1 Score": 0,
      "Faction 1 Chain": 0,
      "Faction 1 Wars Won": 19,
      "Faction 1 Wars Lost": 20,
      "Faction 1 Win Rate": "49%",
      "Faction 1 Rank Value": 9,
      "Faction 1 Respect Value": 230993,
      "Faction 1 HOF Chain Value": 250,
      "Faction 1 Members": 14,
      "Faction 2 ID": 50975,
      "Faction 2 Name": "BASH BACK",
      "Faction 2 Score": 0,
      "Faction 2 Chain": 0,
      "Faction 2 Wars Won": 9,
      "Faction 2 Wars Lost": 3,
      "Faction 2 Win Rate": "75%",
      "Faction 2 Rank Value": 10,
      "Faction 2 Respect Value": 80898,
      "Faction 2 HOF Chain Value": 100,
      "Faction 2 Members": 21,
      "Total Score": 0,
      "Winner Faction ID": "",
      "Last Updated Date": "2025-09-16",
      "Last Updated Time": "10:08",
      "Faction 1 Odds": 2.46,
      "Faction 1 Implied %": "40.60%",
      "Faction 1 True %": "40.60%",
      "Faction 1 Confidence": "95%",
      "Faction 1 Bet Example": "1 Xanax ($744,983) → $1,832,658 (+$1,087,675)",
      "Faction 2 Odds": 1.68,
      "Faction 2 Implied %": "59.40%",
      "Faction 2 True %": "59.40%",
      "Faction 2 Confidence": "65%",
      "Faction 2 Bet Example": "1 Xanax ($744,983) → $1,251,571 (+$506,588)",
      "Overall Confidence": "80%",
      "House Edge %": 6,
      "Rating Ratio": 0.7,
      "Odds Calculated At": "9/17/2025, 1:24:26 PM"
    },
    {
      "War ID": 30864,
      "Status": "Active",
      "Start Date": "2025-09-20",
      "Start Time": "11:00",
      "End Date": "",
      "End Time": "",
      "Duration": "0m",
      "Target Score": 7400,
      "Faction 1 ID": 10463,
      "Faction 1 Name": "Warriors 4077th",
      "Faction 1 Score": 0,
      "Faction 1 Chain": 0,
      "Faction 1 Wars Won": 0,
      "Faction 1 Wars Lost": 2,
      "Faction 1 Win Rate": "0%",
      "Faction 1 Rank Value": 1,
      "Faction 1 Respect Value": 907249,
      "Faction 1 HOF Chain Value": 1000,
      "Faction 1 Members": 52,
      "Faction 2 ID": 51384,
      "Faction 2 Name": "HEART BREAKERS",
      "Faction 2 Score": 0,
      "Faction 2 Chain": 0,
      "Faction 2 Wars Won": 14,
      "Faction 2 Wars Lost": 11,
      "Faction 2 Win Rate": "56%",
      "Faction 2 Rank Value": 11,
      "Faction 2 Respect Value": 204985,
      "Faction 2 HOF Chain Value": 500,
      "Faction 2 Members": 50,
      "Total Score": 0,
      "Winner Faction ID": "",
      "Last Updated Date": "2025-09-16",
      "Last Updated Time": "10:08",
      "Faction 1 Odds": 2.88,
      "Faction 1 Implied %": "34.71%",
      "Faction 1 True %": "34.71%",
      "Faction 1 Confidence": "25%",
      "Faction 1 Bet Example": "1 Xanax ($744,983) → $2,145,551 (+$1,400,568)",
      "Faction 2 Odds": 1.53,
      "Faction 2 Implied %": "65.29%",
      "Faction 2 True %": "65.29%",
      "Faction 2 Confidence": "85%",
      "Faction 2 Bet Example": "1 Xanax ($744,983) → $1,139,824 (+$394,841)",
      "Overall Confidence": "55%",
      "House Edge %": 6,
      "Rating Ratio": 0.54,
      "Odds Calculated At": "9/17/2025, 1:24:28 PM"
    },
    {
      "War ID": 31035,
      "Status": "Active",
      "Start Date": "2025-09-18",
      "Start Time": "10:00",
      "End Date": "",
      "End Time": "",
      "Duration": "0m",
      "Target Score": 18000,
      "Faction 1 ID": 9524,
      "Faction 1 Name": "|HT|",
      "Faction 1 Score": 0,
      "Faction 1 Chain": 0,
      "Faction 1 Wars Won": 50,
      "Faction 1 Wars Lost": 49,
      "Faction 1 Win Rate": "51%",
      "Faction 1 Rank Value": 21,
      "Faction 1 Respect Value": 6752137,
      "Faction 1 HOF Chain Value": 25000,
      "Faction 1 Members": 100,
      "Faction 2 ID": 11747,
      "Faction 2 Name": "Natural Selection II",
      "Faction 2 Score": 0,
      "Faction 2 Chain": 0,
      "Faction 2 Wars Won": 64,
      "Faction 2 Wars Lost": 35,
      "Faction 2 Win Rate": "65%",
      "Faction 2 Rank Value": 21,
      "Faction 2 Respect Value": 18505159,
      "Faction 2 HOF Chain Value": 100000,
      "Faction 2 Members": 96,
      "Total Score": 0,
      "Winner Faction ID": "",
      "Last Updated Date": "2025-09-16",
      "Last Updated Time": "10:08",
      "Faction 1 Odds": 3.34,
      "Faction 1 Implied %": "29.97%",
      "Faction 1 True %": "29.97%",
      "Faction 1 Confidence": "95%",
      "Faction 1 Bet Example": "1 Xanax ($744,983) → $2,488,243 (+$1,743,260)",
      "Faction 2 Odds": 1.43,
      "Faction 2 Implied %": "70.03%",
      "Faction 2 True %": "70.03%",
      "Faction 2 Confidence": "95%",
      "Faction 2 Bet Example": "1 Xanax ($744,983) → $1,065,326 (+$320,343)",
      "Overall Confidence": "95%",
      "House Edge %": 6,
      "Rating Ratio": 0.42,
      "Odds Calculated At": "9/17/2025, 1:24:30 PM"
    },
    {
      "War ID": 31147,
      "Status": "Active",
      "Start Date": "2025-09-19",
      "Start Time": "10:00",
      "End Date": "",
      "End Time": "",
      "Duration": "0m",
      "Target Score": 16000,
      "Faction 1 ID": 937,
      "Faction 1 Name": "Sport Club",
      "Faction 1 Score": 0,
      "Faction 1 Chain": 1,
      "Faction 1 Wars Won": 42,
      "Faction 1 Wars Lost": 47,
      "Faction 1 Win Rate": "47%",
      "Faction 1 Rank Value": 18,
      "Faction 1 Respect Value": 10050471,
      "Faction 1 HOF Chain Value": 25000,
      "Faction 1 Members": 86,
      "Faction 2 ID": 9357,
      "Faction 2 Name": "The Next Level-Mavericks",
      "Faction 2 Score": 0,
      "Faction 2 Chain": 0,
      "Faction 2 Wars Won": 59,
      "Faction 2 Wars Lost": 40,
      "Faction 2 Win Rate": "60%",
      "Faction 2 Rank Value": 18,
      "Faction 2 Respect Value": 7262570,
      "Faction 2 HOF Chain Value": 10000,
      "Faction 2 Members": 83,
      "Total Score": 0,
      "Winner Faction ID": "",
      "Last Updated Date": "2025-09-16",
      "Last Updated Time": "10:08",
      "Faction 1 Odds": 1.77,
      "Faction 1 Implied %": "56.40%",
      "Faction 1 True %": "56.40%",
      "Faction 1 Confidence": "95%",
      "Faction 1 Bet Example": "1 Xanax ($744,983) → $1,318,620 (+$573,637)",
      "Faction 2 Odds": 2.29,
      "Faction 2 Implied %": "43.60%",
      "Faction 2 True %": "43.60%",
      "Faction 2 Confidence": "95%",
      "Faction 2 Bet Example": "1 Xanax ($744,983) → $1,706,011 (+$961,028)",
      "Overall Confidence": "95%",
      "House Edge %": 6,
      "Rating Ratio": 1.25,
      "Odds Calculated At": "9/17/2025, 1:24:32 PM"
    },
    {
      "War ID": 30870,
      "Status": "Active",
      "Start Date": "2025-09-19",
      "Start Time": "16:00",
      "End Date": "",
      "End Time": "",
      "Duration": "0m",
      "Target Score": 3100,
      "Faction 1 ID": 42185,
      "Faction 1 Name": "Bruh.",
      "Faction 1 Score": 0,
      "Faction 1 Chain": 0,
      "Faction 1 Wars Won": 10,
      "Faction 1 Wars Lost": 8,
      "Faction 1 Win Rate": "56%",
      "Faction 1 Rank Value": 7,
      "Faction 1 Respect Value": 262412,
      "Faction 1 HOF Chain Value": 250,
      "Faction 1 Members": 18,
      "Faction 2 ID": 52492,
      "Faction 2 Name": "The Kingsmen",
      "Faction 2 Score": 0,
      "Faction 2 Chain": 0,
      "Faction 2 Wars Won": 10,
      "Faction 2 Wars Lost": 9,
      "Faction 2 Win Rate": "53%",
      "Faction 2 Rank Value": 7,
      "Faction 2 Respect Value": 66150,
      "Faction 2 HOF Chain Value": 50,
      "Faction 2 Members": 14,
      "Total Score": 0,
      "Winner Faction ID": "",
      "Last Updated Date": "2025-09-16",
      "Last Updated Time": "10:08",
      "Faction 1 Odds": 1.94,
      "Faction 1 Implied %": "51.50%",
      "Faction 1 True %": "51.50%",
      "Faction 1 Confidence": "75%",
      "Faction 1 Bet Example": "1 Xanax ($744,983) → $1,445,267 (+$700,284)",
      "Faction 2 Odds": 2.06,
      "Faction 2 Implied %": "48.50%",
      "Faction 2 True %": "48.50%",
      "Faction 2 Confidence": "75%",
      "Faction 2 Bet Example": "1 Xanax ($744,983) → $1,534,665 (+$789,682)",
      "Overall Confidence": "75%",
      "House Edge %": 6,
      "Rating Ratio": 1.05,
      "Odds Calculated At": "9/17/2025, 1:24:34 PM"
    },
    {
      "War ID": 30931,
      "Status": "Active",
      "Start Date": "2025-09-20",
      "Start Time": "16:00",
      "End Date": "",
      "End Time": "",
      "Duration": "0m",
      "Target Score": 8900,
      "Faction 1 ID": 40795,
      "Faction 1 Name": "Sons Of Torn",
      "Faction 1 Score": 0,
      "Faction 1 Chain": 0,
      "Faction 1 Wars Won": 16,
      "Faction 1 Wars Lost": 18,
      "Faction 1 Win Rate": "47%",
      "Faction 1 Rank Value": 8,
      "Faction 1 Respect Value": 762108,
      "Faction 1 HOF Chain Value": 2500,
      "Faction 1 Members": 98,
      "Faction 2 ID": 53254,
      "Faction 2 Name": "New Horizon",
      "Faction 2 Score": 0,
      "Faction 2 Chain": 0,
      "Faction 2 Wars Won": 12,
      "Faction 2 Wars Lost": 11,
      "Faction 2 Win Rate": "52%",
      "Faction 2 Rank Value": 7,
      "Faction 2 Respect Value": 222246,
      "Faction 2 HOF Chain Value": 500,
      "Faction 2 Members": 80,
      "Total Score": 0,
      "Winner Faction ID": "",
      "Last Updated Date": "2025-09-16",
      "Last Updated Time": "10:08",
      "Faction 1 Odds": 2.03,
      "Faction 1 Implied %": "49.34%",
      "Faction 1 True %": "49.34%",
      "Faction 1 Confidence": "95%",
      "Faction 1 Bet Example": "1 Xanax ($744,983) → $1,512,315 (+$767,332)",
      "Faction 2 Odds": 1.97,
      "Faction 2 Implied %": "50.66%",
      "Faction 2 True %": "50.66%",
      "Faction 2 Confidence": "85%",
      "Faction 2 Bet Example": "1 Xanax ($744,983) → $1,467,617 (+$722,634)",
      "Overall Confidence": "90%",
      "House Edge %": 6,
      "Rating Ratio": 0.96,
      "Odds Calculated At": "9/17/2025, 1:24:35 PM"
    },
    {
      "War ID": 30859,
      "Status": "Active",
      "Start Date": "2025-09-18",
      "Start Time": "12:00",
      "End Date": "",
      "End Time": "",
      "Duration": "0m",
      "Target Score": 5400,
      "Faction 1 ID": 42133,
      "Faction 1 Name": "Little Banditos",
      "Faction 1 Score": 0,
      "Faction 1 Chain": 0,
      "Faction 1 Wars Won": 23,
      "Faction 1 Wars Lost": 20,
      "Faction 1 Win Rate": "53%",
      "Faction 1 Rank Value": 8,
      "Faction 1 Respect Value": 429370,
      "Faction 1 HOF Chain Value": 2500,
      "Faction 1 Members": 48,
      "Faction 2 ID": 48097,
      "Faction 2 Name": "Braveheart",
      "Faction 2 Score": 0,
      "Faction 2 Chain": 1,
      "Faction 2 Wars Won": 42,
      "Faction 2 Wars Lost": 49,
      "Faction 2 Win Rate": "46%",
      "Faction 2 Rank Value": 8,
      "Faction 2 Respect Value": 478665,
      "Faction 2 HOF Chain Value": 1000,
      "Faction 2 Members": 50,
      "Total Score": 0,
      "Winner Faction ID": "",
      "Last Updated Date": "2025-09-16",
      "Last Updated Time": "10:08",
      "Faction 1 Odds": 1.9,
      "Faction 1 Implied %": "52.68%",
      "Faction 1 True %": "52.68%",
      "Faction 1 Confidence": "95%",
      "Faction 1 Bet Example": "1 Xanax ($744,983) → $1,415,468 (+$670,485)",
      "Faction 2 Odds": 2.11,
      "Faction 2 Implied %": "47.32%",
      "Faction 2 True %": "47.32%",
      "Faction 2 Confidence": "95%",
      "Faction 2 Bet Example": "1 Xanax ($744,983) → $1,571,914 (+$826,931)",
      "Overall Confidence": "95%",
      "House Edge %": 6,
      "Rating Ratio": 1.11,
      "Odds Calculated At": "9/17/2025, 1:24:37 PM"
    },
    {
      "War ID": 30888,
      "Status": "Active",
      "Start Date": "2025-09-19",
      "Start Time": "15:00",
      "End Date": "",
      "End Time": "",
      "Duration": "0m",
      "Target Score": 2800,
      "Faction 1 ID": 50680,
      "Faction 1 Name": "The Shack",
      "Faction 1 Score": 0,
      "Faction 1 Chain": 0,
      "Faction 1 Wars Won": 25,
      "Faction 1 Wars Lost": 37,
      "Faction 1 Win Rate": "40%",
      "Faction 1 Rank Value": 2,
      "Faction 1 Respect Value": 224190,
      "Faction 1 HOF Chain Value": 250,
      "Faction 1 Members": 34,
      "Faction 2 ID": 52860,
      "Faction 2 Name": "$$$",
      "Faction 2 Score": 0,
      "Faction 2 Chain": 0,
      "Faction 2 Wars Won": 4,
      "Faction 2 Wars Lost": 13,
      "Faction 2 Win Rate": "24%",
      "Faction 2 Rank Value": 2,
      "Faction 2 Respect Value": 60848,
      "Faction 2 HOF Chain Value": 113,
      "Faction 2 Members": 25,
      "Total Score": 0,
      "Winner Faction ID": "",
      "Last Updated Date": "2025-09-16",
      "Last Updated Time": "10:08",
      "Faction 1 Odds": 1.67,
      "Faction 1 Implied %": "59.84%",
      "Faction 1 True %": "59.84%",
      "Faction 1 Confidence": "95%",
      "Faction 1 Bet Example": "1 Xanax ($744,983) → $1,244,122 (+$499,139)",
      "Faction 2 Odds": 2.49,
      "Faction 2 Implied %": "40.16%",
      "Faction 2 True %": "40.16%",
      "Faction 2 Confidence": "75%",
      "Faction 2 Bet Example": "1 Xanax ($744,983) → $1,855,008 (+$1,110,025)",
      "Overall Confidence": "85%",
      "House Edge %": 6,
      "Rating Ratio": 1.43,
      "Odds Calculated At": "9/17/2025, 1:24:39 PM"
    }
  ],
  "count": 10,
  "exported_at": "2025-09-23T14:03:01.909465+00:00",
  "source": "Random Wars Sample",
  "status": "success",
  "metadata": {
    "total_wars": 10,
    "export_timestamp": "2025-09-23T14:03:01.909475+00:00",
    "sheet_name": "Random Wars Sample",
    "spreadsheet_id": "1_pp2DU-znWYe6jpMp29oYicUzPBEQSkhh04_qe6EFbY"
  }
}